httpie_web_bot_auth/__init__.py
httpie_web_bot_auth-0.1.1.dist-info/WHEEL
httpie_web_bot_auth-0.1.1.dist-info/entry_points.txt
httpie_web_bot_auth-0.1.1.dist-info/METADATA
httpie_web_bot_auth-0.1.1.dist-info/RECORD
