Metadata-Version: 2.3
Name: httpie-web-bot-auth
Version: 0.1.1
Summary: HTTPie plugin to sign requests using Web Bot Auth for Ed25519 keys
Author: Thibault Meunier
Author-email: Thibault Meunier <mail@thibaultmeunier.com>
License:                                  Apache License
Requires-Dist: bot-auth>=0.3.1
Requires-Dist: httpie>=3.2.4
Requires-Dist: requests>=2.32.5
Requires-Dist: typing-extensions>=4.15.0
Requires-Python: >=3.12
